nexus_dev/__init__.py
nexus_dev/cli.py
nexus_dev/code_graph.py
nexus_dev/code_graph_js.py
nexus_dev/config.py
nexus_dev/database.py
nexus_dev/embeddings.py
nexus_dev/entity_extractor.py
nexus_dev/github_importer.py
nexus_dev/graph_store.py
nexus_dev/hybrid_db.py
nexus_dev/kv_store.py
nexus_dev/mcp_client.py
nexus_dev/mcp_config.py
nexus_dev/query_router.py
nexus_dev/server.py
nexus_dev/agent_templates/__init__.py
nexus_dev/agent_templates/api_designer.yaml
nexus_dev/agent_templates/code_reviewer.yaml
nexus_dev/agent_templates/debug_detective.yaml
nexus_dev/agent_templates/doc_writer.yaml
nexus_dev/agent_templates/performance_optimizer.yaml
nexus_dev/agent_templates/refactor_architect.yaml
nexus_dev/agent_templates/security_auditor.yaml
nexus_dev/agent_templates/test_engineer.yaml
nexus_dev/agents/__init__.py
nexus_dev/agents/agent_config.py
nexus_dev/agents/agent_executor.py
nexus_dev/agents/agent_manager.py
nexus_dev/agents/prompt_factory.py
nexus_dev/chunkers/__init__.py
nexus_dev/chunkers/base.py
nexus_dev/chunkers/docs_chunker.py
nexus_dev/chunkers/java_chunker.py
nexus_dev/chunkers/javascript_chunker.py
nexus_dev/chunkers/python_chunker.py
nexus_dev/gateway/__init__.py
nexus_dev/gateway/connection_manager.py
nexus_dev/schemas/mcp_config_schema.json
nexus_dev/templates/AGENTS.md
nexus_dev/templates/antigravity_aiexclude
nexus_dev/templates/antigravity_antigravityignore
nexus_dev/templates/antigravity_geminiignore
nexus_dev/templates/pre-commit-hook
nexus_dev-4.0.0.data/data/nexus_dev/agent_templates/__init__.py
nexus_dev-4.0.0.data/data/nexus_dev/agent_templates/api_designer.yaml
nexus_dev-4.0.0.data/data/nexus_dev/agent_templates/code_reviewer.yaml
nexus_dev-4.0.0.data/data/nexus_dev/agent_templates/debug_detective.yaml
nexus_dev-4.0.0.data/data/nexus_dev/agent_templates/doc_writer.yaml
nexus_dev-4.0.0.data/data/nexus_dev/agent_templates/performance_optimizer.yaml
nexus_dev-4.0.0.data/data/nexus_dev/agent_templates/refactor_architect.yaml
nexus_dev-4.0.0.dist-info/METADATA
nexus_dev-4.0.0.dist-info/WHEEL
nexus_dev-4.0.0.dist-info/entry_points.txt
nexus_dev-4.0.0.dist-info/licenses/LICENSE
nexus_dev-4.0.0.dist-info/RECORD
