Metadata-Version: 2.4
Name: nexus-dev
Version: 4.0.0
Summary: MCP server for persistent AI coding assistant memory with local RAG
Project-URL: Homepage, https://github.com/mmornati/nexus-dev
Project-URL: Repository, https://github.com/mmornati/nexus-dev
Project-URL: Issues, https://github.com/mmornati/nexus-dev/issues
Author-email: Marco Mornati <marco@mornati.net>
License: MIT
License-File: LICENSE
Keywords: ai,assistant,coding,lancedb,mcp,rag,vector-database
Classifier: Development Status :: 3 - Alpha
Classifier: Intended Audience :: Developers
Classifier: License :: OSI Approved :: MIT License
Classifier: Programming Language :: Python :: 3.13
Classifier: Topic :: Software Development :: Libraries :: Python Modules
Requires-Python: >=3.13
Requires-Dist: click>=8.1.0
Requires-Dist: falkordblite>=0.7.0
Requires-Dist: httpx>=0.28.0
Requires-Dist: jsonschema>=4.18.0
Requires-Dist: lancedb>=0.26.0
Requires-Dist: mcp>=1.25.0
Requires-Dist: openai>=1.60.0
Requires-Dist: pandas>=2.0.0
Requires-Dist: pyarrow>=18.0.0
Requires-Dist: pydantic>=2.10.0
Requires-Dist: pyyaml>=6.0.0
Requires-Dist: tree-sitter-language-pack>=0.7.0
Requires-Dist: tree-sitter>=0.24.0
Provides-Extra: all
Requires-Dist: boto3>=1.34.0; extra == 'all'
Requires-Dist: cohere>=4.37.0; extra == 'all'
Requires-Dist: google-cloud-aiplatform>=1.38.0; extra == 'all'
Requires-Dist: voyageai>=0.1.0; extra == 'all'
Provides-Extra: aws
Requires-Dist: boto3>=1.34.0; extra == 'aws'
Provides-Extra: cohere
Requires-Dist: cohere>=4.37.0; extra == 'cohere'
Provides-Extra: dev
Requires-Dist: mypy>=1.14.0; extra == 'dev'
Requires-Dist: pytest-asyncio>=0.25.0; extra == 'dev'
Requires-Dist: pytest-cov>=6.0.0; extra == 'dev'
Requires-Dist: pytest>=8.0.0; extra == 'dev'
Requires-Dist: ruff>=0.9.0; extra == 'dev'
Requires-Dist: types-pyyaml>=6.0.0; extra == 'dev'
Provides-Extra: google
Requires-Dist: google-cloud-aiplatform>=1.38.0; extra == 'google'
Provides-Extra: voyage
Requires-Dist: voyageai>=0.1.0; extra == 'voyage'
